README.md
setup.cfg
setup.py
enisebox/__init__.py
enisebox/circle.py
enisebox/enisebox.py
enisebox/image.py
enisebox/polygon.py
enisebox/polytools.py
enisebox/rectangle.py
enisebox/thing.py
enisebox.egg-info/PKG-INFO
enisebox.egg-info/SOURCES.txt
enisebox.egg-info/dependency_links.txt
enisebox.egg-info/requires.txt
enisebox.egg-info/top_level.txt