Metadata-Version: 1.0
Name: enisebox
Version: 0.0.2.1
Summary: A lib for making video games
Home-page: UNKNOWN
Author: BagEddy42
Author-email: Info@enise.fr
License: UNKNOWN
Keywords: game,physics
Platform: UNKNOWN
